MANIFEST.in
README.md
setup.py
c_kaleido/include/1bpp.h
c_kaleido/include/2bpp.h
c_kaleido/include/4bpp.h
c_kaleido/src/1bpp.c
c_kaleido/src/2bpp.c
c_kaleido/src/4bpp.c
c_kaleido/src/c_kaleido.c
epd/__init__.py
epd/image.py
epd/tcm3_usb.py
epd.egg-info/PKG-INFO
epd.egg-info/SOURCES.txt
epd.egg-info/dependency_links.txt
epd.egg-info/top_level.txt
epd/convert/__init__.py
epd/tcm/TCGen1.py
epd/tcm/TCGen2.py
epd/tcm/TCGen3.py
epd/tcm/__init__.py
epd/tcm/tcm102.py
epd/tcm/tcm113.py
epd/tcm/tcm133.py
epd/tcm/tcm27.py
epd/tcm/tcm280.py
epd/tcm/tcm312.py
epd/tcm/tcm74.py
epd/tcm/tcm97.py
epdconvert/include/Chunks.h
epdconvert/include/Compression.h
epdconvert/include/Flip.h
epdconvert/include/Invert.h
epdconvert/include/Type0.h
epdconvert/include/Type2.h
epdconvert/include/Type7.h
epdconvert/include/crc32.h
epdconvert/include/lz.h
epdconvert/src/Chunks.c
epdconvert/src/Compression.c
epdconvert/src/Flip.c
epdconvert/src/Invert.c
epdconvert/src/Type0.c
epdconvert/src/Type2.c
epdconvert/src/Type7.c
epdconvert/src/crc32.c
epdconvert/src/epdconvert.c
epdconvert/src/lz.c