Metadata-Version: 2.1
Name: epd
Version: 3.0.2
Summary: EPD library for MpicoSys Timing Controllers (TC/TCM), including color conversion
Home-page: https://www.mpicosys.com/
Author: Paweł Musiał, MpicoSys
Author-email: pawel.musial@mpicosys.com
Requires: Pillow
Requires: hashlib
